<?xml version="1.0" encoding="UTF-8"?>
<!DOCTYPE mapper
  PUBLIC "-//mybatis.org//DTD Mapper 3.0//EN"
  "https://mybatis.org/dtd/mybatis-3-mapper.dtd">

<mapper namespace="com.spring.dao.admin.AdminClassDAO">

    <resultMap id="AdminClassListResultMap" type="com.spring.dto.admin.AdminClassListDTO">
        <result property="classId" column="class_id"/>
        <result property="className" column="class_name"/>
        <result property="teacherName" column="teacher_name"/>
        <result property="studentCount" column="student_count"/>
        <result property="classStatus" column="class_status"/>
        <result property="createdAt" column="created_at"/>
    </resultMap>

    <select id="selectClassList" resultMap="AdminClassListResultMap">
        SELECT
            c.class_id,
            c.class_name,
            NVL(MAX(t.teacher_name), '-') AS teacher_name,
            COUNT(DISTINCT sc.student_id) AS student_count,
            c.class_status,
            c.created_at
        FROM class c
        LEFT JOIN teacher_class tc ON c.class_id = tc.class_id
        LEFT JOIN teacher t ON tc.teacher_id = t.teacher_id
        LEFT JOIN student_class sc ON c.class_id = sc.class_id
        WHERE c.class_status != 'DELETED'
        GROUP BY
            c.class_id,
            c.class_name,
            c.class_status,
            c.created_at
        ORDER BY c.class_id DESC
    </select>

    <update id="updateClassStatus">
        UPDATE class
        SET class_status = #{classStatus},
            updated_at = SYSDATE
        WHERE class_id = #{classId}
    </update>
    <select id="selectActiveClassCount" resultType="int">
    SELECT COUNT(*)
    FROM CLASS
    WHERE CLASS_STATUS = 'ACTIVE'
</select>

</mapper>